ovpn_manager/__init__.py
ovpn_manager/model.py
ovpn_manager/vpn_manager.py
ovpn_manager-1.1.0.dist-info/METADATA
ovpn_manager-1.1.0.dist-info/WHEEL
ovpn_manager-1.1.0.dist-info/RECORD
