Metadata-Version: 2.1
Name: ovpn_manager
Version: 1.1.0
Summary: Python library interaction with openVPN manager interface
Project-URL: Homepage, https://github.com/shizacat/py_openvpn_manager_interface
Author: Alexey Matveev
Classifier: License :: OSI Approved :: MIT License
Classifier: Operating System :: OS Independent
Classifier: Programming Language :: Python :: 3
Classifier: Programming Language :: Python :: 3.8
Classifier: Programming Language :: Python :: 3.9
Classifier: Programming Language :: Python :: 3.10
Classifier: Topic :: Software Development :: Libraries :: Python Modules
Requires-Python: >=3.8
